{
    "type":"Scene",
    "props":{
        "width":750,
        "visible":true,
        "top":0,
        "right":0,
        "left":0,
        "height":1334,
        "bottom":0
    },
    "compId":2,
    "child":[
        {
            "type":"Image",
            "props":{
                "y":1,
                "x":0,
                "top":1,
                "right":0,
                "name":"TouchEvent",
                "left":0,
                "bottom":0
            },
            "compId":221,
            "child":[
                {
                    "type":"Script",
                    "props":{
                        "runtime":"script/GameMgr3d/GameInputCtrl.ts"
                    },
                    "compId":222
                }
            ]
        },
        {
            "type":"Image",
            "props":{
                "top":1,
                "right":0,
                "name":"mouseTouch",
                "left":0,
                "bottom":0
            },
            "compId":43
        },
        {
            "type":"Image",
            "props":{
                "y":2,
                "x":0,
                "top":1,
                "right":0,
                "name":"touchBeginnerGuide",
                "mouseThrough":true,
                "left":0,
                "bottom":0
            },
            "compId":172,
            "child":[
                {
                    "type":"Image",
                    "props":{
                        "y":248,
                        "x":159,
                        "width":432,
                        "skin":"mainview/kuan-di@2x.png",
                        "sizeGrid":"20,20,20,20",
                        "name":"BeginnerGuide",
                        "height":278
                    },
                    "compId":190,
                    "child":[
                        {
                            "type":"Image",
                            "props":{
                                "y":42,
                                "x":92,
                                "width":247,
                                "skin":"mainview/img_guideInfo.png.png",
                                "height":187
                            },
                            "compId":174
                        }
                    ]
                },
                {
                    "type":"Image",
                    "props":{
                        "y":1070,
                        "x":332,
                        "width":84,
                        "skin":"mainview/img_hand.png",
                        "scaleY":1,
                        "scaleX":1,
                        "name":"hand",
                        "height":92,
                        "anchorY":0,
                        "anchorX":0
                    },
                    "compId":176
                }
            ]
        },
        {
            "type":"Text",
            "props":{
                "y":270,
                "x":574,
                "width":52,
                "text":"超越",
                "name":"surpassOtherText",
                "height":26,
                "fontSize":26,
                "color":"#2B2B2B",
                "runtime":"laya.display.Text"
            },
            "compId":146
        },
        {
            "type":"Image",
            "props":{
                "y":96,
                "x":375,
                "name":"progress"
            },
            "compId":164,
            "child":[
                {
                    "type":"Image",
                    "props":{
                        "y":31,
                        "x":128,
                        "skin":"game/4@2x.png",
                        "name":"imgNextLevel",
                        "anchorY":0.5,
                        "anchorX":0.5
                    },
                    "compId":168,
                    "child":[
                        {
                            "type":"FontClip",
                            "props":{
                                "y":32,
                                "x":32,
                                "value":"18",
                                "skin":"game/shuzi-jd1@2x.png",
                                "sheet":"0123456789",
                                "name":"nextLevelLab",
                                "anchorY":0.5,
                                "anchorX":0.5,
                                "align":"center"
                            },
                            "compId":203
                        }
                    ]
                },
                {
                    "type":"Image",
                    "props":{
                        "y":32,
                        "x":-128,
                        "skin":"game/4@2x.png",
                        "name":"imgCurrLevel",
                        "anchorY":0.5,
                        "anchorX":0.5
                    },
                    "compId":192,
                    "child":[
                        {
                            "type":"FontClip",
                            "props":{
                                "y":32,
                                "x":32,
                                "value":"17",
                                "skin":"game/shuzi-jd1@2x.png",
                                "sheet":"0123456789",
                                "name":"currLevelLab",
                                "anchorY":0.5,
                                "anchorX":0.5,
                                "align":"center"
                            },
                            "compId":204
                        }
                    ]
                },
                {
                    "type":"Image",
                    "props":{
                        "y":32,
                        "x":0,
                        "name":"passNodeParent"
                    },
                    "compId":207
                }
            ]
        },
        {
            "type":"Image",
            "props":{
                "y":679,
                "x":624,
                "width":120,
                "visible":false,
                "skin":"SkinTrial/tiaoguod@2x.png",
                "sizeGrid":"10,10,10,10",
                "name":"ballNum",
                "height":110
            },
            "compId":194,
            "child":[
                {
                    "type":"Image",
                    "props":{
                        "y":8,
                        "x":33,
                        "skin":"SkinTrial/qiu3@2x.png"
                    },
                    "compId":225
                },
                {
                    "type":"Image",
                    "props":{
                        "y":74,
                        "x":27,
                        "skin":"SkinTrial/shenyu@2x.png"
                    },
                    "compId":224
                },
                {
                    "type":"Image",
                    "props":{
                        "y":77,
                        "x":77,
                        "skin":"SkinTrial/shenyu3@2x.png",
                        "name":"num"
                    },
                    "compId":226
                }
            ]
        },
        {
            "type":"Button",
            "props":{
                "y":679,
                "x":624,
                "visible":false,
                "stateNum":1,
                "skin":"SkinTrial/tiaoguod@2x.png",
                "name":"jumpBtn",
                "hitTestPrior":true
            },
            "compId":213,
            "child":[
                {
                    "type":"Image",
                    "props":{
                        "y":42,
                        "x":60,
                        "skin":"SkinTrial/tiaoguo_ship@2x.png",
                        "anchorY":0.5,
                        "anchorX":0.5
                    },
                    "compId":219
                },
                {
                    "type":"Sprite",
                    "props":{
                        "y":74,
                        "x":18,
                        "texture":"SkinTrial/tiaoguo@2x.png"
                    },
                    "compId":220
                }
            ]
        },

        {
            "type":"Button",
            "props":{
                "y":679,
                "x":7,
                "width":120,
                "visible":false,
                "stateNum":1,
                "skin":"SkinTrial/wudi@2x.png",
                "name":"invincibleBtn",
                "hitTestPrior":true,
                "height":110
            },
            "compId":215,
            "child":[
                {
                    "type":"Image",
                    "props":{
                        "skin":"SkinTrial/wudi_ship@2x.png",
                        "name":"noHave",
                        "centerY":32,
                        "centerX":0
                    },
                    "compId":216
                },
                {
                    "type":"Image",
                    "props":{
                        "skin":"SkinTrial/wudi_shengyu@2x.png",
                        "name":"have",
                        "centerY":32,
                        "centerX":0
                    },
                    "compId":217
                },
                {
                    "type":"Image",
                    "props":{
                        "y":41,
                        "x":59,
                        "skin":"SkinTrial/wudiqiu@2x.png",
                        "scaleY":1,
                        "scaleX":1,
                        "anchorY":0.5,
                        "anchorX":0.5
                    },
                    "compId":218
                }
            ]
        },
        {
            "type":"Script",
            "props":{
                "runtime":"script/UiViews/GameFighting.ts"
            },
            "compId":214
        },
        {
            "type":"Image",
            "props":{
                "y":428,
                "x":89,
                "width":115,
                "visible":true,
                "name":"AD1",
                "height":147,
                "anchorY":0.5,
                "anchorX":0.5
            },
            "compId":227,
            "child":[
                {
                    "type":"Script",
                    "props":{
                        "runtime":"script/UiViews/PromotionAnimation.ts"
                    },
                    "compId":229
                }
            ]
        },
        {
            "type":"Image",
            "props":{
                "y":425,
                "x":681,
                "width":115,
                "visible":true,
                "name":"AD2",
                "height":147,
                "anchorY":0.5,
                "anchorX":0.5
            },
            "compId":228,
            "child":[
                {
                    "type":"Script",
                    "props":{
                        "runtime":"script/UiViews/PromotionAnimation.ts"
                    },
                    "compId":230
                }
            ]
        },
        {
            "type":"Image",
            "props":{
                "top":50,
                "skin":"game/yad.png",
                "name":"yad",
                "scaleX":0.7,
                "scaleY":0.7,
                "left":20
            },
            "compId":231
        }
    ],
    "animations":[
        {
            "nodes":[
                {
                    "target":176,
                    "keyframes":{
                        "scaleY":[
                            {
                                "value":1,
                                "tweenMethod":"linearNone",
                                "tween":true,
                                "target":176,
                                "key":"scaleY",
                                "index":0
                            },
                            {
                                "value":1.2,
                                "tweenMethod":"linearNone",
                                "tween":true,
                                "target":176,
                                "key":"scaleY",
                                "index":10
                            },
                            {
                                "value":1,
                                "tweenMethod":"linearNone",
                                "tween":true,
                                "target":176,
                                "key":"scaleY",
                                "index":20
                            }
                        ],
                        "scaleX":[
                            {
                                "value":1,
                                "tweenMethod":"linearNone",
                                "tween":true,
                                "target":176,
                                "key":"scaleX",
                                "index":0
                            },
                            {
                                "value":1.2,
                                "tweenMethod":"linearNone",
                                "tween":true,
                                "target":176,
                                "key":"scaleX",
                                "index":10
                            },
                            {
                                "value":1,
                                "tweenMethod":"linearNone",
                                "tween":true,
                                "target":176,
                                "key":"scaleX",
                                "index":20
                            }
                        ]
                    }
                }
            ],
            "name":"BeginnerGuide",
            "id":3,
            "frameRate":24,
            "action":2
        },
        {
            "nodes":[
                {
                    "target":218,
                    "keyframes":{
                        "scaleY":[
                            {
                                "value":1,
                                "tweenMethod":"linearNone",
                                "tween":true,
                                "target":218,
                                "key":"scaleY",
                                "index":0
                            },
                            {
                                "value":1.2,
                                "tweenMethod":"linearNone",
                                "tween":true,
                                "target":218,
                                "key":"scaleY",
                                "index":10
                            },
                            {
                                "value":1,
                                "tweenMethod":"linearNone",
                                "tween":true,
                                "target":218,
                                "key":"scaleY",
                                "index":20
                            }
                        ],
                        "scaleX":[
                            {
                                "value":1,
                                "tweenMethod":"linearNone",
                                "tween":true,
                                "target":218,
                                "key":"scaleX",
                                "index":0
                            },
                            {
                                "value":1.2,
                                "tweenMethod":"linearNone",
                                "tween":true,
                                "target":218,
                                "key":"scaleX",
                                "index":10
                            },
                            {
                                "value":1,
                                "tweenMethod":"linearNone",
                                "tween":true,
                                "target":218,
                                "key":"scaleX",
                                "index":20
                            }
                        ]
                    }
                }
            ],
            "name":"invincibleBallAnim",
            "id":4,
            "frameRate":24,
            "action":2
        },
        {
            "nodes":[
                {
                    "target":219,
                    "keyframes":{
                        "scaleY":[
                            {
                                "value":1,
                                "tweenMethod":"linearNone",
                                "tween":true,
                                "target":219,
                                "key":"scaleY",
                                "index":0
                            },
                            {
                                "value":1.2,
                                "tweenMethod":"linearNone",
                                "tween":true,
                                "target":219,
                                "key":"scaleY",
                                "index":10
                            },
                            {
                                "value":1,
                                "tweenMethod":"linearNone",
                                "tween":true,
                                "target":219,
                                "key":"scaleY",
                                "index":20
                            }
                        ],
                        "scaleX":[
                            {
                                "value":1,
                                "tweenMethod":"linearNone",
                                "tween":true,
                                "target":219,
                                "key":"scaleX",
                                "index":0
                            },
                            {
                                "value":1.2,
                                "tweenMethod":"linearNone",
                                "tween":true,
                                "target":219,
                                "key":"scaleX",
                                "index":10
                            },
                            {
                                "value":1,
                                "tweenMethod":"linearNone",
                                "tween":true,
                                "target":219,
                                "key":"scaleX",
                                "index":20
                            }
                        ]
                    }
                }
            ],
            "name":"jumpBtnAnim",
            "id":5,
            "frameRate":24,
            "action":2
        }
    ],
    "loadList":[
        "mainview/kuan-di@2x.png",
        "mainview/img_guideInfo.png.png",
        "mainview/img_hand.png",
        "game/4@2x.png",
        "game/shuzi-jd1@2x.png",
        "SkinTrial/tiaoguod@2x.png",
        "SkinTrial/qiu3@2x.png",
        "SkinTrial/shenyu@2x.png",
        "SkinTrial/shenyu3@2x.png",
        "SkinTrial/tiaoguo_ship@2x.png",
        "SkinTrial/tiaoguo@2x.png",
        "SkinTrial/wudi@2x.png",
        "SkinTrial/wudi_ship@2x.png",
        "SkinTrial/wudi_shengyu@2x.png",
        "SkinTrial/wudiqiu@2x.png"
    ],
    "loadList3D":[

    ]
}