{
    "type":"Scene",
    "props":{
        "windowAry":"@arr:@node:6,,,,",
        "width":720,
        "height":1280
    },
    "compId":2,
    "child":[
        {
            "type":"Script",
            "props":{
                "windowAry":"@arr:@node:6,@node:66,@node:68,@node:122,",
                "runtime":"Core/UIModule/UIManager.ts"
            },
            "compId":4
        },
        {
            "type":"Script",
            "props":{
                "runtime":"Game/GameData.ts"
            },
            "compId":3
        },
        {
            "type":"View",
            "props":{
                "top":0,
                "right":0,
                "name":"GameView",
                "left":0,
                "btnAry":"@arr:,,",
                "bottom":0
            },
            "compId":6,
            "child":[
                {
                    "type":"Script",
                    "props":{
                        "starAry":"@arr:@node:96,@node:97,@node:98",
                        "spriteImg":"@node:30",
                        "runtime":"UI/GameView.ts",
                        "progress":"@node:23",
                        "levelLabel":"@node:22",
                        "btnTestAry":"@arr:@node:102,@node:105",
                        "btnSetting":"@node:16",
                        "btnReset":"@node:15",
                        "btnLabelAry":"@arr:@node:92,@node:94,@node:95",
                        "btnColorAry":"@arr:@node:52,@node:51,@node:50",
                        "btnClose":"@node:157",
                        "btnAry":"@arr:@node:35,@node:38,@node:40",
                        "btn3":"@node:40",
                        "btn2":"@node:38",
                        "guide":"@node:166",
                        "btn1":"@node:35"
                        
                    },
                    "compId":48
                },
                {
                    "type":"Image",
                    "props":{
                        "width":720,
                        "visible":false,
                        "skin":"game/bg.jpg",
                        "sizeGrid":"1,1,1,1",
                        "height":1560,
                        "centerY":0,
                        "centerX":0
                    },
                    "compId":14
                },
                {
                    "type":"View",
                    "props":{
                        "y":0,
                        "x":0,
                        "width":728,
                        "name":"TopView",
                        "height":206
                    },
                    "compId":20,
                    "child":[
                        {
                            "type":"Button",
                            "props":{
                                "y":54,
                                "x":54,
                                "width":64,
                                "var":"ResetBtn",
                                "stateNum":1,
                                "skin":"game/redo.png",
                                "runtime":"Core/UIModule/Common/btnRunTime.ts",
                                "height":64,
                                "anchorY":0.5,
                                "anchorX":0.5
                            },
                            "compId":15
                        },
                        {
                            "type":"Image",
                            "props":{
                                "y":63,
                                "x":266,
                                "width":48,
                                "skin":"game/star.png",
                                "name":"starBg1",
                                "height":48
                            },
                            "compId":19
                        },
                        {
                            "type":"Image",
                            "props":{
                                "y":63,
                                "x":336,
                                "width":48,
                                "skin":"game/star.png",
                                "name":"starBg2",
                                "height":48
                            },
                            "compId":18
                        },
                        {
                            "type":"Image",
                            "props":{
                                "y":63,
                                "x":406,
                                "width":48,
                                "skin":"game/star.png",
                                "name":"starBg3",
                                "height":48
                            },
                            "compId":17
                        },
                        {
                            "type":"Label",
                            "props":{
                                "y":140,
                                "x":9.9716796875,
                                "var":"Tips",
                                "text":"Level",
                                "fontSize":39,
                                "color":"#ffffff",
                                "bold":true
                            },
                            "compId":21
                        },
                        {
                            "type":"Label",
                            "props":{
                                "y":139,
                                "x":121,
                                "var":"Level",
                                "text":"2",
                                "fontSize":39,
                                "color":"#ffffff",
                                "bold":true
                            },
                            "compId":22
                        },
                        {
                            "type":"ProgressBar",
                            "props":{
                                "y":139,
                                "x":226,
                                "width":267,
                                "value":0.5,
                                "skin":"game/jindutiao_lv.png",
                                "sizeGrid":"18,18,18,18",
                                "height":37
                            },
                            "compId":23
                        },
                        {
                            "type":"Image",
                            "props":{
                                "y":63,
                                "x":266,
                                "width":48,
                                "skin":"game/star_colored.png",
                                "name":"star1",
                                "height":48
                            },
                            "compId":96
                        },
                        {
                            "type":"Image",
                            "props":{
                                "y":63,
                                "x":336,
                                "width":48,
                                "skin":"game/star_colored.png",
                                "name":"star2",
                                "height":48
                            },
                            "compId":97
                        },
                        {
                            "type":"Image",
                            "props":{
                                "y":63,
                                "x":406,
                                "width":48,
                                "visible":false,
                                "skin":"game/star_colored.png",
                                "name":"star3",
                                "height":48
                            },
                            "compId":98
                        }
                    ]
                },
                {
                    "type":"Image",
                    "props":{
                        "y":486,
                        "x":1,
                        "width":164,
                        "height":280
                    },
                    "compId":28,
                    "child":[
                        {
                            "type":"Image",
                            "props":{
                                "width":152,
                                "skin":"game/preview.png",
                                "sizeGrid":"98,66,103,60",
                                "height":246,
                                "centerY":0,
                                "centerX":0
                            },
                            "compId":100
                        },
                        {
                            "type":"Sprite",
                            "props":{
                                "y":0,
                                "x":0,
                                "width":164,
                                "name":"preview",
                                "height":280
                            },
                            "compId":30,
                            "child":[
                                {
                                    "type":"Script",
                                    "props":{
                                        "runtime":"UI/IcePreview.ts",
                                        "modelScale":0.5
                                    },
                                    "compId":99
                                }
                            ]
                        }
                    ]
                },
                {
                    "type":"View",
                    "props":{
                        "width":720,
                        "height":1000,
                        "centerX":0,
                        "bottom":100,
                        "anchorY":0.5,
                        "anchorX":0.5
                    },
                    "compId":24,
                    "child":[
                        {
                            "type":"Image",
                            "props":{
                                "y":0,
                                "x":18,
                                "width":676,
                                "visible":false,
                                "skin":"game/panelUp.jpg",
                                "sizeGrid":"1,1,1,1",
                                "name":"bgUp",
                                "height":530
                            },
                            "compId":25
                        },
                        {
                            "type":"Image",
                            "props":{
                                "y":530,
                                "x":18,
                                "width":676,
                                "visible":false,
                                "skin":"game/panelDown.jpg",
                                "sizeGrid":"1,1,1,1",
                                "name":"bgDown",
                                "height":530
                            },
                            "compId":27
                        },
                        {
                            "type":"Image",
                            "props":{
                                "y":-204,
                                "x":0,
                                "visible":false,
                                "skin":"game/IMG_3433.jpg"
                            },
                            "compId":54
                        },
                        {
                            "type":"Button",
                            "props":{
                                "y":764,
                                "x":160,
                                "stateNum":1,
                                "skin":"game/btn.png",
                                "bottom":180,
                                "anchorY":0.5,
                                "anchorX":0.5
                            },
                            "compId":35,
                            "child":[
                                {
                                    "type":"Sprite",
                                    "props":{
                                        "y":6,
                                        "x":6
                                    },
                                    "compId":52,
                                    "child":[
                                        {
                                            "type":"Circle",
                                            "props":{
                                                "y":52,
                                                "x":52,
                                                "radius":52,
                                                "lineWidth":1,
                                                "fillColor":"#c1ff61"
                                            },
                                            "compId":42
                                        },
                                        {
                                            "type":"Label",
                                            "props":{
                                                "y":32,
                                                "x":41,
                                                "text":"1",
                                                "fontSize":40
                                            },
                                            "compId":163
                                        }
                                    ]
                                }
                            ]
                        },
                        {
                            "type":"Button",
                            "props":{
                                "y":764,
                                "x":356,
                                "stateNum":1,
                                "skin":"game/btn.png",
                                "bottom":180,
                                "anchorY":0.5,
                                "anchorX":0.5
                            },
                            "compId":38,
                            "child":[
                                {
                                    "type":"Sprite",
                                    "props":{
                                        "y":6,
                                        "x":6
                                    },
                                    "compId":51,
                                    "child":[
                                        {
                                            "type":"Circle",
                                            "props":{
                                                "y":52,
                                                "x":52,
                                                "radius":52,
                                                "lineWidth":1,
                                                "fillColor":"#85604d"
                                            },
                                            "compId":44
                                        },
                                        {
                                            "type":"Label",
                                            "props":{
                                                "y":32,
                                                "x":41,
                                                "text":"2",
                                                "fontSize":40
                                            },
                                            "compId":164
                                        }
                                    ]
                                }
                            ]
                        },
                        {
                            "type":"Button",
                            "props":{
                                "y":764,
                                "x":551,
                                "stateNum":1,
                                "skin":"game/btn.png",
                                "bottom":180,
                                "anchorY":0.5,
                                "anchorX":0.5
                            },
                            "compId":40,
                            "child":[
                                {
                                    "type":"Sprite",
                                    "props":{
                                        "y":6,
                                        "x":6
                                    },
                                    "compId":50,
                                    "child":[
                                        {
                                            "type":"Circle",
                                            "props":{
                                                "y":52,
                                                "x":52,
                                                "radius":52,
                                                "lineWidth":1,
                                                "fillColor":"#5cfdc1"
                                            },
                                            "compId":45
                                        },
                                        {
                                            "type":"Label",
                                            "props":{
                                                "y":32,
                                                "x":41,
                                                "text":"3",
                                                "fontSize":40
                                            },
                                            "compId":165
                                        }
                                    ]
                                }
                            ]
                        },
                        {
                            "type":"Label",
                            "props":{
                                "y":860,
                                "x":160,
                                "valign":"middle",
                                "text":"label",
                                "fontSize":30,
                                "color":"#ffffff",
                                "bottom":130,
                                "bold":true,
                                "anchorY":0.5,
                                "anchorX":0.5,
                                "align":"center"
                            },
                            "compId":92
                        },
                        {
                            "type":"Label",
                            "props":{
                                "y":860,
                                "x":360,
                                "valign":"middle",
                                "text":"label",
                                "fontSize":30,
                                "color":"#ffffff",
                                "bottom":130,
                                "bold":true,
                                "anchorY":0.5,
                                "anchorX":0.5,
                                "align":"center"
                            },
                            "compId":94
                        },
                        {
                            "type":"Label",
                            "props":{
                                "y":860,
                                "x":551,
                                "valign":"middle",
                                "text":"label",
                                "fontSize":30,
                                "color":"#ffffff",
                                "bottom":130,
                                "bold":true,
                                "anchorY":0.5,
                                "anchorX":0.5,
                                "align":"center"
                            },
                            "compId":95
                        },
                        {
                            "type":"Button",
                            "props":{
                                "y":981,
                                "x":265,
                                "visible":false,
                                "stateNum":1,
                                "skin":"game/btn.png",
                                "anchorY":0.5,
                                "anchorX":0.5
                            },
                            "compId":102,
                            "child":[
                                {
                                    "type":"Label",
                                    "props":{
                                        "text":"1",
                                        "fontSize":40,
                                        "centerY":0,
                                        "centerX":0
                                    },
                                    "compId":108
                                }
                            ]
                        },
                        {
                            "type":"Button",
                            "props":{
                                "y":981,
                                "x":462,
                                "visible":false,
                                "stateNum":1,
                                "skin":"game/btn.png",
                                "anchorY":0.5,
                                "anchorX":0.5
                            },
                            "compId":105,
                            "child":[
                                {
                                    "type":"Label",
                                    "props":{
                                        "y":0,
                                        "x":0,
                                        "text":"2",
                                        "fontSize":40,
                                        "centerY":0,
                                        "centerX":0
                                    },
                                    "compId":109
                                }
                            ]
                        },
                        {
                            "type":"Label",
                            "props":{
                                "x":360,
                                "var":"guide",
                                "valign":"middle",
                                "text":"Press the number 2 and 3 at the same time",
                                "fontSize":32,
                                "color":"#ffffff",
                                "bottom":52,
                                "bold":true,
                                "anchorY":0.5,
                                "anchorX":0.5,
                                "align":"center"
                            },
                            "compId":166
                        }
                    ]
                }
            ]
        },
        {
            "type":"View",
            "props":{
                "top":0,
                "right":0,
                "name":"HomeView",
                "left":0,
                "bottom":0
            },
            "compId":66,
            "child":[
                {
                    "type":"Script",
                    "props":{
                        "spriteImg":"@node:116",
                        "runtime":"UI/HomeView.ts",
                        "musicBtn":"@node:121",
                        "levelLabel":"@node:136",
                        "btnStart":"@node:71",
                        "btnShare":"@node:158",
                        "btnNext":"@node:137",
                        "btnClose":"@node:139"
                    },
                    "compId":69
                },
                {
                    "type":"Image",
                    "props":{
                        "top":0,
                        "skin":"game/loadBg.png"
                    },
                    "compId":70
                },
                {
                    "type":"Sprite",
                    "props":{
                        "y":256,
                        "x":0,
                        "width":720,
                        "height":720
                    },
                    "compId":116,
                    "child":[
                        {
                            "type":"Script",
                            "props":{
                                "runtime":"UI/IcePreview.ts",
                                "modelScale":1.5
                            },
                            "compId":117
                        }
                    ]
                },
                {
                    "type":"Button",
                    "props":{
                        "y":932,
                        "stateNum":1,
                        "skin":"game/startGame.png",
                        "runtime":"Core/UIModule/Common/btnRunTime.ts",
                        "name":"btnStart",
                        "centerX":0
                    },
                    "compId":71
                },
                {
                    "type":"CheckBox",
                    "props":{
                        "y":14,
                        "x":14,
                        "stateNum":2,
                        "skin":"game/yinxiao.png"
                    },
                    "compId":121
                },
                {
                    "type":"Label",
                    "props":{
                        "y":343,
                        "text":"Level 2",
                        "fontSize":39,
                        "color":"#ffffff",
                        "centerX":0,
                        "bold":true
                    },
                    "compId":136
                },
                {
                    "type":"Button",
                    "props":{
                        "stateNum":1,
                        "skin":"game/startGame.png",
                        "runtime":"Core/UIModule/Common/btnRunTime.ts",
                        "name":"btnNext",
                        "centerX":0,
                        "bottom":0
                    },
                    "compId":137
                },
                {
                    "type":"Image",
                    "props":{
                        "y":150,
                        "skin":"game/logo.png",
                        "centerX":9
                    },
                    "compId":154
                },
                {
                    "type":"HSlider",
                    "props":{
                        "y":950,
                        "x":-3,
                        "width":723,
                        "visible":false,
                        "skin":"game/common/hslider.png",
                        "height":100
                    },
                    "compId":156
                }
            ]
        },
        {
            "type":"View",
            "props":{
                "top":0,
                "right":0,
                "name":"GameEnd",
                "left":0,
                "bottom":0
            },
            "compId":68,
            "child":[
                {
                    "type":"Script",
                    "props":{
                        "starAry":"@arr:@node:89,@node:90,@node:91",
                        "spriteImg":"@arr:@node:110,@node:112",
                        "runtime":"UI/GameEndView.ts",
                        "progress":"@node:82",
                        "percent":"@node:83",
                        "btnVideo":"@node:75",
                        "btnStart":"@node:78",
                        "btnShare":"@node:159",
                        "btnRestart":"@node:118"
                    },
                    "compId":73
                },
                {
                    "type":"Image",
                    "props":{
                        "y":0,
                        "x":0,
                        "width":720,
                        "visible":false,
                        "skin":"game/mask.png",
                        "sizeGrid":"1,1,1,1",
                        "height":1560,
                        "alpha":0.6
                    },
                    "compId":141
                },
                {
                    "type":"Image",
                    "props":{
                        "y":0,
                        "x":0,
                        "skin":"game/bg_w.jpg",
                        "sizeGrid":"1,1,1,1",
                        "centerY":0,
                        "centerX":0,
                        "alpha":0.1
                    },
                    "compId":74
                },
                {
                    "type":"Button",
                    "props":{
                        "width":220,
                        "stateNum":1,
                        "skin":"game/button_1.png",
                        "sizeGrid":"16,17,23,17",
                        "runtime":"Core/UIModule/Common/btnRunTime.ts",
                        "name":"btnVideo",
                        "height":123,
                        "centerY":220,
                        "centerX":-130
                    },
                    "compId":75,
                    "child":[
                        {
                            "type":"Image",
                            "props":{
                                "y":11,
                                "skin":"game/ad.png",
                                "centerX":0
                            },
                            "compId":76
                        },
                        {
                            "type":"Label",
                            "props":{
                                "y":81,
                                "valign":"middle",
                                "text":"REPLAY",
                                "fontSize":26,
                                "color":"#ffffff",
                                "centerX":0,
                                "bold":true,
                                "align":"center"
                            },
                            "compId":77
                        }
                    ]
                },
                {
                    "type":"Button",
                    "props":{
                        "width":220,
                        "stateNum":1,
                        "skin":"game/button_3.png",
                        "sizeGrid":"16,17,23,17",
                        "runtime":"Core/UIModule/Common/btnRunTime.ts",
                        "name":"btnStart",
                        "height":123,
                        "centerY":220,
                        "centerX":130
                    },
                    "compId":78,
                    "child":[
                        {
                            "type":"Image",
                            "props":{
                                "skin":"game/UI_30.png",
                                "centerY":0,
                                "centerX":0,
                                "alpha":0.8
                            },
                            "compId":79
                        }
                    ]
                },
                {
                    "type":"Button",
                    "props":{
                        "y":799,
                        "width":220,
                        "stateNum":1,
                        "skin":"game/button_2.png",
                        "sizeGrid":"16,17,23,17",
                        "runtime":"Core/UIModule/Common/btnRunTime.ts",
                        "name":"btnRestart",
                        "height":123,
                        "centerY":220,
                        "centerX":0
                    },
                    "compId":118,
                    "child":[
                        {
                            "type":"Image",
                            "props":{
                                "skin":"game/redo.png",
                                "scaleY":0.8,
                                "scaleX":0.8,
                                "centerY":-17,
                                "centerX":0,
                                "alpha":0.8
                            },
                            "compId":119
                        },
                        {
                            "type":"Label",
                            "props":{
                                "y":81,
                                "x":0,
                                "valign":"middle",
                                "text":"RESTART",
                                "fontSize":26,
                                "color":"#ffffff",
                                "centerX":0,
                                "bold":true,
                                "align":"center"
                            },
                            "compId":120
                        }
                    ]
                },
                {
                    "type":"Image",
                    "props":{
                        "width":601,
                        "skin":"game/tankuang_bg.png",
                        "sizeGrid":"203,271,197,288",
                        "height":598,
                        "centerY":-189,
                        "centerX":0
                    },
                    "compId":81,
                    "child":[
                        {
                            "type":"Image",
                            "props":{
                                "y":33,
                                "width":48,
                                "skin":"game/star.png",
                                "name":"starBg1",
                                "height":48,
                                "centerX":-100
                            },
                            "compId":84
                        },
                        {
                            "type":"Image",
                            "props":{
                                "y":33,
                                "width":48,
                                "skin":"game/star.png",
                                "name":"starBg2",
                                "height":48,
                                "centerX":0
                            },
                            "compId":85
                        },
                        {
                            "type":"Image",
                            "props":{
                                "y":33,
                                "width":48,
                                "skin":"game/star.png",
                                "name":"starBg3",
                                "height":48,
                                "centerX":100
                            },
                            "compId":86
                        },
                        {
                            "type":"Image",
                            "props":{
                                "y":33,
                                "x":0,
                                "width":48,
                                "skin":"game/star_colored.png",
                                "name":"star1",
                                "height":48,
                                "centerX":-100
                            },
                            "compId":89
                        },
                        {
                            "type":"Image",
                            "props":{
                                "y":33,
                                "x":0,
                                "width":48,
                                "skin":"game/star_colored.png",
                                "name":"star2",
                                "height":48,
                                "centerX":0
                            },
                            "compId":90
                        },
                        {
                            "type":"Image",
                            "props":{
                                "y":33,
                                "x":0,
                                "width":48,
                                "skin":"game/star_colored.png",
                                "name":"star3",
                                "height":48,
                                "centerX":100
                            },
                            "compId":91
                        },
                        {
                            "type":"ProgressBar",
                            "props":{
                                "y":205,
                                "width":451,
                                "value":1,
                                "skin":"game/jindutiao_lan.png",
                                "sizeGrid":"18,18,18,18",
                                "height":37,
                                "centerX":0
                            },
                            "compId":82
                        },
                        {
                            "type":"Label",
                            "props":{
                                "y":141,
                                "x":178.244140625,
                                "valign":"middle",
                                "text":"Finshed 90%",
                                "fontSize":40,
                                "color":"#0070ff",
                                "bold":true,
                                "align":"left"
                            },
                            "compId":83
                        },
                        {
                            "type":"Image",
                            "props":{
                                "y":299,
                                "width":220,
                                "skin":"game/match.jpg",
                                "sizeGrid":"10,10,10,10",
                                "height":220,
                                "centerX":-124
                            },
                            "compId":87,
                            "child":[
                                {
                                    "type":"Sprite",
                                    "props":{
                                        "y":0,
                                        "x":0,
                                        "width":220,
                                        "name":"preview",
                                        "height":220
                                    },
                                    "compId":110,
                                    "child":[
                                        {
                                            "type":"Script",
                                            "props":{
                                                "runtime":"UI/IcePreview.ts",
                                                "modelScale":0.5
                                            },
                                            "compId":111
                                        }
                                    ]
                                }
                            ]
                        },
                        {
                            "type":"Image",
                            "props":{
                                "y":299,
                                "width":220,
                                "skin":"game/match.jpg",
                                "sizeGrid":"10,10,10,10",
                                "height":220,
                                "centerX":124
                            },
                            "compId":88,
                            "child":[
                                {
                                    "type":"Sprite",
                                    "props":{
                                        "y":0,
                                        "x":0,
                                        "width":220,
                                        "name":"preview",
                                        "height":220
                                    },
                                    "compId":112,
                                    "child":[
                                        {
                                            "type":"Script",
                                            "props":{
                                                "runtime":"UI/IcePreview.ts",
                                                "modelScale":0.5
                                            },
                                            "compId":113
                                        }
                                    ]
                                }
                            ]
                        }
                    ]
                }
            ]
        },
        {
            "type":"View",
            "props":{
                "top":0,
                "right":0,
                "name":"PausedView",
                "left":0,
                "bottom":0
            },
            "compId":122,
            "child":[
                {
                    "type":"Script",
                    "props":{
                        "spriteImg":"@node:124",
                        "runtime":"UI/PausedView.ts",
                        "btnRestart":"@node:129",
                        "btnHome":"@node:126",
                        "btnContinue":"@node:132"
                    },
                    "compId":123
                },
                {
                    "type":"Image",
                    "props":{
                        "y":0,
                        "x":0,
                        "width":720,
                        "skin":"game/mask.png",
                        "sizeGrid":"1,1,1,1",
                        "height":1560
                    },
                    "compId":135
                },
                {
                    "type":"Label",
                    "props":{
                        "y":213,
                        "text":"PAUSE",
                        "fontSize":90,
                        "color":"#189d86",
                        "centerX":0,
                        "bold":true
                    },
                    "compId":125
                },
                {
                    "type":"Button",
                    "props":{
                        "y":456,
                        "x":132,
                        "width":457,
                        "stateNum":1,
                        "skin":"game/button_5.png",
                        "sizeGrid":"16,17,23,17",
                        "runtime":"Core/UIModule/Common/btnRunTime.ts",
                        "name":"btnHome",
                        "height":135,
                        "centerY":-117,
                        "centerX":0
                    },
                    "compId":126,
                    "child":[
                        {
                            "type":"Image",
                            "props":{
                                "skin":"game/home.png",
                                "scaleY":0.8,
                                "scaleX":0.8,
                                "centerY":-6,
                                "centerX":-165,
                                "alpha":0.8
                            },
                            "compId":127
                        },
                        {
                            "type":"Label",
                            "props":{
                                "y":34.5,
                                "valign":"middle",
                                "text":"HOME",
                                "fontSize":60,
                                "color":"#ffffff",
                                "centerX":22,
                                "bold":true,
                                "align":"center"
                            },
                            "compId":128
                        }
                    ]
                },
                {
                    "type":"Button",
                    "props":{
                        "y":645,
                        "x":132,
                        "width":457,
                        "stateNum":1,
                        "skin":"game/button_4.png",
                        "sizeGrid":"16,17,23,17",
                        "runtime":"Core/UIModule/Common/btnRunTime.ts",
                        "name":"btnRestart",
                        "height":135,
                        "centerY":72,
                        "centerX":0
                    },
                    "compId":129,
                    "child":[
                        {
                            "type":"Image",
                            "props":{
                                "skin":"game/restart.png",
                                "scaleY":0.8,
                                "scaleX":0.8,
                                "centerY":-6,
                                "centerX":-165,
                                "alpha":0.8
                            },
                            "compId":130
                        },
                        {
                            "type":"Label",
                            "props":{
                                "y":34.5,
                                "valign":"middle",
                                "text":"RESTART",
                                "fontSize":60,
                                "color":"#ffffff",
                                "centerX":22,
                                "bold":true,
                                "align":"center"
                            },
                            "compId":131
                        }
                    ]
                },
                {
                    "type":"Button",
                    "props":{
                        "y":833,
                        "x":132,
                        "width":457,
                        "stateNum":1,
                        "skin":"game/button_2.png",
                        "sizeGrid":"16,17,23,17",
                        "runtime":"Core/UIModule/Common/btnRunTime.ts",
                        "name":"btnContinue",
                        "height":135,
                        "centerY":260,
                        "centerX":0
                    },
                    "compId":132,
                    "child":[
                        {
                            "type":"Image",
                            "props":{
                                "skin":"game/play.png",
                                "scaleY":0.8,
                                "scaleX":0.8,
                                "centerY":-6,
                                "centerX":-165,
                                "alpha":0.8
                            },
                            "compId":133
                        },
                        {
                            "type":"Label",
                            "props":{
                                "y":34.5,
                                "valign":"middle",
                                "text":"CONTINUE",
                                "fontSize":60,
                                "color":"#ffffff",
                                "centerX":22,
                                "bold":true,
                                "align":"center"
                            },
                            "compId":134
                        }
                    ]
                }
            ]
        }
    ],
    "loadList":[
        "game/bg.jpg",
        "game/redo.png",
        "game/star.png",
        "game/jindutiao_lv.png",
        "game/star_colored.png",
        "game/preview.png",
        "game/panelUp.jpg",
        "game/panelDown.jpg",
        "game/IMG_3433.jpg",
        "game/btn.png",
        "game/close.png",
        "game/loadBg.png",
        "game/startGame.png",
        "game/yinxiao.png",
        "game/logo.png",
        "game/common/hslider.png",

        "game/mask.png",
        "game/bg_w.jpg",
        "game/button_1.png",
        "game/ad.png",
        "game/button_3.png",
        "game/UI_30.png",
        "game/button_2.png",
        "game/tankuang_bg.png",
        "game/jindutiao_lan.png",
        "game/match.jpg",
        "game/button_5.png",
        "game/share.png",
        "game/home.png",
        "game/button_4.png",
        "game/restart.png",
        "game/play.png"
    ],
    "loadList3D":[

    ]
}