{"type":"View","props":{"width":750,"top":0,"right":0,"left":0,"height":1334,"bottom":0},"compId":2,"child":[{"type":"Image","props":{"top":0,"skin":"ui/common/skin/bg_.png","sizeGrid":"1,1,1,1","right":0,"name":"fullUI","left":0,"bottom":0,"alpha":1},"compId":183},{"type":"Box","props":{"y":0,"x":0,"width":750,"name":"topUI","height":640},"compId":51,"child":[{"type":"Button","props":{"y":567,"x":135,"stateNum":1,"skin":"ui/common/skin/btnBack.png","name":"backBtn","anchorY":0.5,"anchorX":0.5},"compId":49},{"type":"Sprite","props":{"y":60,"x":24,"texture":"ui/common/home/goldBg.png","scaleY":1,"scaleX":1,"name":"coinBg"},"compId":523,"child":[{"type":"Image","props":{"top":2,"skin":"ui/common/home/diamond2.png","scaleY":0.5,"scaleX":0.5,"left":2},"compId":524},{"type":"Text","props":{"y":8,"x":22,"width":200,"valign":"middle","text":"9999","runtime":"Laya.Text","name":"value","fontSize":45,"font":"Arial","color":"#ffffff","bold":true,"align":"center"},"compId":525}]}]},{"type":"Box","props":{"width":750,"name":"middleUI","height":2,"centerY":0,"centerX":0},"compId":181,"child":[{"type":"Box","props":{"y":113,"x":0,"width":750,"name":"skinPanel","height":30},"compId":6,"child":[{"type":"Image","props":{"y":-162,"x":0,"skin":"ui/common/skin/bg12.png","name":"bg"},"compId":182},{"type":"Image","props":{"y":-52,"x":375,"visible":false,"skin":"ui/common/skinWeapon/tip1.png","name":"weapon","anchorY":0.5,"anchorX":0.5,"alpha":0},"compId":527},{"type":"Image","props":{"y":-114,"x":138,"width":144,"scaleY":1.4,"scaleX":1.4,"pivotX":72,"name":"role1","height":168},"compId":7,"child":[{"type":"Image","props":{"y":0,"x":0,"width":144,"skin":"ui/common/skin/select.png","scaleY":1,"scaleX":1,"name":"img1","height":168},"compId":180},{"type":"Image","props":{"y":0,"x":0,"skin":"ui/common/skinWeapon/bg12.png","name":"img2"},"compId":199},{"type":"Image","props":{"y":32,"x":20,"skin":"ui/common/game/weapon/weapon_02.png","scaleY":0.7,"scaleX":0.7,"name":"icon"},"compId":8},{"type":"Image","props":{"y":123,"x":40,"visible":true,"skin":"ui/common/skin/btn_xianzhong.png","name":"lock"},"compId":9},{"type":"Image","props":{"y":0,"x":0,"width":144,"skin":"ui/common/skin/mask.png","sizeGrid":"35,23,34,30","name":"txt","height":168},"compId":219,"child":[{"type":"Image","props":{"y":54,"x":47,"skin":"ui/common/skin/btn_suo.png"},"compId":517}]}]},{"type":"Image","props":{"y":-114,"x":373,"width":144,"scaleY":1.4,"scaleX":1.4,"pivotX":72,"name":"role2","height":168},"compId":528,"child":[{"type":"Image","props":{"y":0,"x":0,"width":144,"skin":"ui/common/skin/select.png","scaleY":1,"scaleX":1,"name":"img1","height":168},"compId":529},{"type":"Image","props":{"y":0,"x":0,"skin":"ui/common/skinWeapon/bg12.png","name":"img2"},"compId":530},{"type":"Image","props":{"y":32,"x":20,"skin":"ui/common/game/weapon/weapon_04.png","scaleY":0.7,"scaleX":0.7,"name":"icon"},"compId":531},{"type":"Image","props":{"y":123,"x":40,"visible":true,"skin":"ui/common/skin/btn_xianzhong.png","name":"lock"},"compId":532},{"type":"Image","props":{"y":0,"x":0,"width":144,"skin":"ui/common/skin/mask.png","sizeGrid":"35,23,34,30","name":"txt","height":168},"compId":533,"child":[{"type":"Image","props":{"y":54,"x":47,"skin":"ui/common/skin/btn_suo.png"},"compId":534}]}]},{"type":"Image","props":{"y":-114,"x":620,"width":144,"scaleY":1.4,"scaleX":1.4,"pivotX":72,"name":"role3","height":168},"compId":535,"child":[{"type":"Image","props":{"y":0,"x":0,"width":144,"skin":"ui/common/skin/select.png","scaleY":1,"scaleX":1,"name":"img1","height":168},"compId":537},{"type":"Image","props":{"y":0,"x":0,"skin":"ui/common/skinWeapon/bg12.png","name":"img2"},"compId":538},{"type":"Image","props":{"y":32,"x":20,"skin":"ui/common/game/weapon/weapon_07.png","scaleY":0.7,"scaleX":0.7,"name":"icon"},"compId":539},{"type":"Image","props":{"y":123,"x":40,"visible":true,"skin":"ui/common/skin/btn_xianzhong.png","name":"lock"},"compId":540},{"type":"Image","props":{"y":0,"x":0,"width":144,"skin":"ui/common/skin/mask.png","sizeGrid":"35,23,34,30","name":"txt","height":168},"compId":541,"child":[{"type":"Image","props":{"y":54,"x":47,"skin":"ui/common/skin/btn_suo.png"},"compId":542}]}]},{"type":"Image","props":{"y":159,"x":138,"width":144,"scaleY":1.4,"scaleX":1.4,"pivotX":72,"name":"role4","height":168},"compId":536,"child":[{"type":"Image","props":{"y":0,"x":0,"width":144,"skin":"ui/common/skin/select.png","scaleY":1,"scaleX":1,"name":"img1","height":168},"compId":543},{"type":"Image","props":{"y":0,"x":0,"skin":"ui/common/skinWeapon/bg12.png","name":"img2"},"compId":544},{"type":"Image","props":{"y":32,"x":20,"skin":"ui/common/game/weapon/weapon_10.png","scaleY":0.7,"scaleX":0.7,"name":"icon"},"compId":545},{"type":"Image","props":{"y":123,"x":40,"visible":true,"skin":"ui/common/skin/btn_xianzhong.png","name":"lock"},"compId":546},{"type":"Image","props":{"y":0,"x":0,"width":144,"skin":"ui/common/skin/mask.png","sizeGrid":"35,23,34,30","name":"txt","height":168},"compId":547,"child":[{"type":"Image","props":{"y":54,"x":47,"skin":"ui/common/skin/btn_suo.png"},"compId":548}]}]},{"type":"Image","props":{"y":159,"x":373,"width":144,"scaleY":1.4,"scaleX":1.4,"pivotX":72,"name":"role5","height":168},"compId":549,"child":[{"type":"Image","props":{"y":0,"x":0,"width":144,"skin":"ui/common/skin/select.png","scaleY":1,"scaleX":1,"name":"img1","height":168},"compId":551},{"type":"Image","props":{"y":0,"x":0,"skin":"ui/common/skinWeapon/bg12.png","name":"img2"},"compId":552},{"type":"Image","props":{"y":32,"x":20,"skin":"ui/common/game/weapon/weapon_13.png","scaleY":0.7,"scaleX":0.7,"name":"icon"},"compId":553},{"type":"Image","props":{"y":123,"x":40,"visible":true,"skin":"ui/common/skin/btn_xianzhong.png","name":"lock"},"compId":554},{"type":"Image","props":{"y":0,"x":0,"width":144,"skin":"ui/common/skin/mask.png","sizeGrid":"35,23,34,30","name":"txt","height":168},"compId":555,"child":[{"type":"Image","props":{"y":54,"x":47,"skin":"ui/common/skin/btn_suo.png"},"compId":556}]}]},{"type":"Image","props":{"y":159,"x":620,"width":144,"scaleY":1.4,"scaleX":1.4,"pivotX":72,"name":"role6","height":168},"compId":550,"child":[{"type":"Image","props":{"y":0,"x":0,"width":144,"skin":"ui/common/skin/select.png","scaleY":1,"scaleX":1,"name":"img1","height":168},"compId":557},{"type":"Image","props":{"y":0,"x":0,"skin":"ui/common/skinWeapon/bg12.png","name":"img2"},"compId":558},{"type":"Image","props":{"y":32,"x":20,"skin":"ui/common/game/weapon/weapon_19.png","scaleY":0.7,"scaleX":0.7,"name":"icon"},"compId":559},{"type":"Image","props":{"y":123,"x":40,"visible":true,"skin":"ui/common/skin/btn_xianzhong.png","name":"lock"},"compId":560},{"type":"Image","props":{"y":0,"x":0,"width":144,"skin":"ui/common/skin/mask.png","sizeGrid":"35,23,34,30","name":"txt","height":168},"compId":561,"child":[{"type":"Image","props":{"y":54,"x":47,"skin":"ui/common/skin/btn_suo.png"},"compId":562}]}]}]},{"type":"Button","props":{"y":590,"x":209,"stateNum":1,"skin":"ui/common/skinWeapon/btn_goumaidaguo.png","name":"unLockBtn","anchorY":0.5,"anchorX":0.5},"compId":287},{"type":"Button","props":{"y":589,"x":559,"stateNum":1,"skin":"ui/common/skin/btn_huoqujinbi.png","name":"getBtn","anchorY":0.5,"anchorX":0.5},"compId":290,"child":[{"type":"Image","props":{"y":26,"x":217,"width":57,"visible":false,"skin":"ui/common/home/img_guanggao.png","name":"img","height":44,"alpha":0},"compId":291}]},{"type":"Image","props":{"y":-327,"x":375,"visible":false,"skin":"ui/common/skin/light.png","name":"light","anchorY":0.5,"anchorX":0.5},"compId":198}]},{"type":"Box","props":{"y":1167,"width":750,"name":"bottomUI","height":1},"compId":44},{"type":"Script","props":{"runtime":"scripts/stackIOViews/skinShopWeapon.ts"},"compId":526}],"loadList":["ui/common/skin/bg_.png","ui/common/skin/btnBack.png","ui/common/home/goldBg.png","ui/common/home/diamond2.png","ui/common/skin/bg12.png","ui/common/skinWeapon/tip1.png","ui/common/skin/select.png","ui/common/skinWeapon/bg12.png","ui/common/game/weapon/weapon_02.png","ui/common/skin/btn_xianzhong.png","ui/common/skin/mask.png","ui/common/skin/btn_suo.png","ui/common/game/weapon/weapon_04.png","ui/common/game/weapon/weapon_07.png","ui/common/game/weapon/weapon_10.png","ui/common/game/weapon/weapon_13.png","ui/common/game/weapon/weapon_19.png","ui/common/skin/light.png","ui/common/skinWeapon/btn_goumaidaguo.png","ui/common/skin/btn_huoqujinbi.png","ui/common/home/img_guanggao.png"],"loadList3D":[]}