{
    "x":0,
    "type":"Scene",
    "selectedBox":2,
    "selecteID":7,
    "searchKey":"Scene",
    "props":{"width":750,"height":1334},
    "nodeParent":-1,
    "maxID":26,
    "loadList3D":[
        ],
    "loadList":[
        "commom/mask.png",
        "commom/num_1.png",
        "summaryView/failImg.png",
        "summaryView/adBg.png",
        "commom/btnBg_gree.png",
        "summaryView/homeBtn.png",
        "summaryView/nextBtn.png",
        "summaryView/shareBtn.png",
        "summaryView/adListHeadImg.png"],
    "label":"Scene",
    "isOpen":true,
    "isDirectory":true,
    "isAniNode":true,
    "hasChild":true,
    "compId":2,
    "child":[
        {
            "x":15,
            "type":"Image",
            "searchKey":"Image",
            "props":{"top":0,"skin":"commom/mask.png","right":0,"left":0,"cacheAs":"normal","bottom":0},
            "nodeParent":2,
            "label":"Image",
            "isDirectory":false,
            "isAniNode":true,
            "hasChild":false,
            "compId":14,
            "child":[
                ]
        },
        {
            "x":15,
            "type":"Box",
            "searchKey":"Box,levelNumBox,levelNumBox",
            "props":{"width":750,"var":"levelNumBox","top":210,"name":"levelNumBox","height":50,"centerX":0},
            "nodeParent":2,
            "label":"levelNumBox",
            "isOpen":true,
            "isDirectory":true,
            "isAniNode":true,
            "hasChild":true,
            "compId":4,
            "child":[
                {
                    "x":30,
                    "type":"FontClip",
                    "searchKey":"FontClip,levelNumLab,levelNumLab",
                    "props":{"y":0,"width":462,"var":"levelNumLab","value":"22","skin":"commom/num_1.png","sheet":"-0123456789","scaleY":0.5,"scaleX":0.5,"name":"levelNumLab","height":100,"centerX":119,"align":"left"},
                    "nodeParent":4,
                    "label":"levelNumLab",
                    "isDirectory":false,
                    "isAniNode":true,
                    "hasChild":false,
                    "compId":5,
                    "child":[
                        ]
                },
                {
                    "x":30,
                    "type":"Label",
                    "searchKey":"Label",
                    "props":{"y":0,"x":250,"width":98,"valign":"middle","text":"Level","height":50,"fontSize":40,"color":"#ffffff","cacheAs":"normal","align":"left"},
                    "nodeParent":4,
                    "label":"Label",
                    "isDirectory":false,
                    "isAniNode":true,
                    "hasChild":false,
                    "compId":6,
                    "child":[
                        ]
                }]
        },
        {
            "x":15,
            "type":"Image",
            "searchKey":"Image,summaryReultImg,summaryReultImg",
            "props":{"var":"summaryReultImg","top":416,"skin":"summaryView/failImg.png","name":"summaryReultImg","centerX":0,"cacheAs":"normal"},
            "nodeParent":2,
            "label":"summaryReultImg",
            "isDirectory":false,
            "isAniNode":true,
            "hasChild":false,
            "compId":7,
            "child":[
                ]
        },
        {
            "x":15,
            "type":"Box",
            "searchKey":"Box,wrongClickBox,wrongClickBox",
            "props":{"y":774,"width":750,"var":"wrongClickBox","name":"wrongClickBox","height":108,"centerX":0,"cacheAs":"normal"},
            "nodeParent":2,
            "label":"wrongClickBox",
            "isOpen":true,
            "isDirectory":true,
            "isAniNode":true,
            "hasChild":true,
            "compId":18,
            "child":[
                {
                    "x":30,
                    "type":"Button",
                    "searchKey":"Button,btn_result,btn_result",
                    "props":{"y":0,"x":215,"var":"btn_result","stateNum":"1","skin":"commom/btnBg_gree.png","name":"btn_result","centerY":0,"centerX":0},
                    "nodeParent":18,
                    "label":"btn_result",
                    "isOpen":true,
                    "isDirectory":false,
                    "isAniNode":true,
                    "hasChild":false,
                    "compId":12,
                    "child":[
                        ]
                },
                {
                    "x":30,
                    "type":"Button",
                    "searchKey":"Button,homeBtn,homeBtn",
                    "props":{"var":"homeBtn","stateNum":1,"skin":"summaryView/homeBtn.png","name":"homeBtn","centerY":0,"centerX":-256},
                    "nodeParent":18,
                    "label":"homeBtn",
                    "isDirectory":false,
                    "isAniNode":true,
                    "hasChild":false,
                    "compId":11,
                    "child":[
                        ]
                },
                {
                    "x":30,
                    "type":"Button",
                    "searchKey":"Button,resultBtn,resultBtn",
                    "props":{"y":27,"x":268,"var":"resultBtn","stateNum":1,"skin":"summaryView/nextBtn.png","name":"resultBtn","mouseEnabled":false,"centerY":0,"centerX":0},
                    "nodeParent":18,
                    "label":"resultBtn",
                    "isDirectory":false,
                    "isAniNode":true,
                    "hasChild":false,
                    "compId":10,
                    "child":[
                        ]
                }]
        },
        {
            "x":15,
            "type":"Script",
            "switchAble":true,
            "source":"src/script/popPanel/SummaryPanel.ts",
            "searchKey":"Script,SummaryPanel",
            "removeAble":true,
            "props":{"runtime":"script/popPanel/SummaryPanel.ts"},
            "nodeParent":2,
            "label":"SummaryPanel",
            "isDirectory":false,
            "isAniNode":true,
            "hasChild":false,
            "compId":13,
            "child":[
                ]
        }],
    "animations":[
        {
            "nodes":[
                ],
            "name":"ani1",
            "id":1,
            "frameRate":24,
            "action":0
        }]
}